annoying/__init__.py
annoying/main.py
annoying-0.1.0.dist-info/METADATA
annoying-0.1.0.dist-info/WHEEL
annoying-0.1.0.dist-info/top_level.txt
annoying-0.1.0.dist-info/RECORD
