Metadata-Version: 2.1
Name: annoying
Version: 0.1.0
Summary: My first Python package
Home-page: UNKNOWN
Author: Peyton
Author-email: <pbabcock@g.emporia.edu>
License: UNKNOWN
Keywords: python,simpleCalpackage
Platform: UNKNOWN
Classifier: Development Status :: 3 - Alpha
Classifier: Intended Audience :: Education
Classifier: Programming Language :: Python :: 2
Classifier: Programming Language :: Python :: 3
Classifier: Operating System :: MacOS :: MacOS X
Classifier: Operating System :: Microsoft :: Windows
